pymcd/__init__.py
pymcd/mcd.py
pymcd-0.2.1.dist-info/METADATA
pymcd-0.2.1.dist-info/WHEEL
pymcd-0.2.1.dist-info/top_level.txt
pymcd-0.2.1.dist-info/RECORD
