Metadata-Version: 2.1
Name: pymcd
Version: 0.2.1
Summary: Calculate Mel-Cepstral Distortion (MCD)
Home-page: https://github.com/chenqi008/pymcd
Author: QiChen
Author-email: <chenqi.china@outlook.com>
License: MIT
Keywords: python,Mel-Cepstral Distortion (MCD)
Platform: UNKNOWN
Classifier: Programming Language :: Python :: 3
Requires-Dist: librosa
Requires-Dist: numpy
Requires-Dist: pyworld
Requires-Dist: pysptk
Requires-Dist: fastdtw
Requires-Dist: scipy
